{"name": "storage", "type": "trait", "description": "Add storages on K8s pod for your workload which follows the pod spec in path 'spec.template'.", "parameters": [{"usage": "Declare pvc type storage", "mandatory": false, "name": "pvc", "type": "[...{"}, {"usage": "Declare config map type storage", "mandatory": false, "name": "configMap", "type": "[...{"}, {"usage": "Declare secret type storage", "mandatory": false, "name": "secret", "type": "[...{"}, {"usage": "Declare empty dir type storage", "mandatory": false, "name": "emptyDir", "type": "[...{"}, {"usage": "Declare host path type storage", "mandatory": false, "name": "hostPath", "type": "[...{"}]}